llm_text_generation/__init__.py
llm_text_generation/model.py
llm_text_generation/version.py
llm_text_generation/api/__init__.py
llm_text_generation/api/cli.py
llm_text_generation/api/generator.py
llm_text_generation/api/server.py
llm_text_generation/api/train.py
llm_text_generation/api/utils.py
llm_text_generation-0.1.1.dist-info/LICENSE
llm_text_generation-0.1.1.dist-info/METADATA
llm_text_generation-0.1.1.dist-info/WHEEL
llm_text_generation-0.1.1.dist-info/entry_points.txt
llm_text_generation-0.1.1.dist-info/top_level.txt
llm_text_generation-0.1.1.dist-info/RECORD
