Metadata-Version: 2.1
Name: llm_text_generation
Version: 0.1.1
Summary: Run large language models.
Author-email: Sebastian Walter <swalter@cs.uni-freiburg.de>
License:                                  Apache License
Project-URL: Github, https://github.com/bastiscode/llm-text-generation
Keywords: nlp,text,llm
Classifier: Programming Language :: Python :: 3
Classifier: Topic :: Scientific/Engineering :: Artificial Intelligence
Classifier: Topic :: Software Development :: Libraries
Classifier: Topic :: Text Processing
Requires-Python: >=3.10
License-File: LICENSE
Requires-Dist: dtpu==0.6.0
Requires-Dist: transformers>=4.42.0
Requires-Dist: peft>=0.11.0
Requires-Dist: flask_socketio>=5.3
Requires-Dist: braceexpand>=0.1.7
Requires-Dist: grammar-utils>=0.1.0
